discord/ext/test/__init__.py
discord/ext/test/_types.py
discord/ext/test/backend.py
discord/ext/test/callbacks.py
discord/ext/test/factories.py
discord/ext/test/runner.py
discord/ext/test/state.py
discord/ext/test/utils.py
discord/ext/test/verify.py
discord/ext/test/voice.py
discord/ext/test/websocket.py
dpytest-0.7.0.dist-info/LICENSE
dpytest-0.7.0.dist-info/METADATA
dpytest-0.7.0.dist-info/WHEEL
dpytest-0.7.0.dist-info/top_level.txt
dpytest-0.7.0.dist-info/RECORD
