Metadata-Version: 2.1
Name: dpytest
Version: 0.7.0
Summary: A package that assists in writing tests for discord.py
Author-email: Rune Tynan <runetynan@gmail.com>
Maintainer: CraftSpider, Sergeileduc
License: The MIT License (MIT)
Project-URL: Homepage, https://github.com/CraftSpider/dpytest
Project-URL: Source, https://github.com/CraftSpider/dpytest
Project-URL: Bug Tracker, https://github.com/CraftSpider/dpytest/issues
Project-URL: Documentation, https://dpytest.readthedocs.io/
Keywords: discord,discord.py,test
Classifier: Programming Language :: Python :: 3.8
Classifier: Programming Language :: Python :: 3.9
Classifier: Programming Language :: Python :: 3.10
Classifier: Programming Language :: Python :: 3.11
Classifier: License :: OSI Approved :: MIT License
Classifier: Operating System :: OS Independent
Classifier: Development Status :: 3 - Alpha
Classifier: Topic :: Software Development :: Testing
Requires-Python: >=3.8
Provides-Extra: test
Provides-Extra: doc
Provides-Extra: dev
License-File: LICENSE
